pyautomouse/__init__.py
pyautomouse-0.1.7.dist-info/LICENSE
pyautomouse-0.1.7.dist-info/METADATA
pyautomouse-0.1.7.dist-info/WHEEL
pyautomouse-0.1.7.dist-info/top_level.txt
pyautomouse-0.1.7.dist-info/RECORD
